joselib/__init__.py
joselib/backends.py
joselib/constants.py
joselib/exceptions.py
joselib/jwe.py
joselib/jwk.py
joselib/jws.py
joselib/jwt.py
joselib/py.typed
joselib/utils.py
joselib-0.1.0b0.dist-info/METADATA
joselib-0.1.0b0.dist-info/WHEEL
joselib-0.1.0b0.dist-info/RECORD
