Metadata-Version: 2.1
Name: joselib
Version: 0.1.0b0
Summary: JOSE implementation in Python
Home-page: https://joselib.readthedocs.io/en/stable/
License: LGPL-3.0+
Keywords: jose,jws,jwe,jwt,json,web,token,security,signing
Author: Stephanos Kuma
Author-email: stephanos@kuma.ai
Requires-Python: >=3.8,<4.0
Classifier: Development Status :: 4 - Beta
Classifier: Intended Audience :: Developers
Classifier: License :: OSI Approved :: GNU Lesser General Public License v3 or later (LGPLv3+)
Classifier: Programming Language :: Python :: 3
Classifier: Programming Language :: Python :: 3.8
Classifier: Programming Language :: Python :: 3.9
Classifier: Programming Language :: Python :: 3.10
Classifier: Programming Language :: Python :: 3.11
Classifier: Programming Language :: Python :: 3.12
Classifier: Topic :: Utilities
Requires-Dist: cryptography (>3.4)
Project-URL: Documentation, https://joselib.readthedocs.io/en/stable/
Project-URL: Repository, https://github.com/spapanik/joselib
